autoflow/__init__.py
autoflow/autoflow.py
autoflow/flowbuilder.py
autoflow/test.py
autoflow/utils.py
autoflow/version.py
videoflow_factory/__init__.py
videoflow_factory/flowbuilder.py
videoflow_factory/utils.py
videoflow_factory/version.py
videoflow_factory/videoflow_factory.py
videoflow_factory-0.0.4.dist-info/METADATA
videoflow_factory-0.0.4.dist-info/WHEEL
videoflow_factory-0.0.4.dist-info/top_level.txt
videoflow_factory-0.0.4.dist-info/RECORD
