Metadata-Version: 2.1
Name: videoflow-factory
Version: 0.0.4
Summary: videoflow_factory
Home-page: https://github.com/kaushikb11/videoflow-factory
Author: Kaushik Bokka
Author-email: kaushikbokka@gmail.com
License: MIT
Platform: UNKNOWN
